tradinghours/__init__.py
tradinghours/client.py
tradinghours/config.py
tradinghours/console.py
tradinghours/currency.py
tradinghours/exceptions.py
tradinghours/market.py
tradinghours/models.py
tradinghours/store.py
tradinghours/util.py
tradinghours/validate.py
tradinghours/server/__init__.py
tradinghours/server/responses.py
tradinghours/server/server.py
tradinghours/server/util.py
tradinghours-0.6.0.dist-info/entry_points.txt
tradinghours-0.6.0.dist-info/licenses/LICENSE
tradinghours-0.6.0.dist-info/WHEEL
tradinghours-0.6.0.dist-info/METADATA
tradinghours-0.6.0.dist-info/RECORD
