Metadata-Version: 2.4
Name: tradinghours
Version: 0.6.0
Summary: TradingHours Library
Author-email: TradingHours <developer@tradinghours.com>
Requires-Python: >=3.9
Classifier: Programming Language :: Python :: 3
Classifier: Operating System :: OS Independent
Classifier: Development Status :: 1 - Planning
Classifier: Intended Audience :: Developers
Classifier: Intended Audience :: Financial and Insurance Industry
Classifier: Topic :: Office/Business :: Financial
Classifier: Topic :: Software Development :: Libraries
License-File: LICENSE
Requires-Dist: tzdata
Requires-Dist: requests
Requires-Dist: sqlalchemy
Requires-Dist: flit ; extra == "dev"
Requires-Dist: isort ; extra == "dev"
Requires-Dist: flake8 ; extra == "dev"
Requires-Dist: flake8-pyproject ; extra == "dev"
Requires-Dist: black ; extra == "dev"
Requires-Dist: coverage[toml] ; extra == "dev"
Requires-Dist: pytest ; extra == "dev"
Requires-Dist: pytest-mock ; extra == "dev"
Requires-Dist: httpx ; extra == "dev"
Requires-Dist: fastapi ; extra == "dev"
Requires-Dist: boto3 ; extra == "dev"
Requires-Dist: boto3 ; extra == "s3"
Requires-Dist: fastapi ; extra == "server"
Requires-Dist: uvicorn[standard] ; extra == "server"
Requires-Dist: gunicorn ; extra == "server"
Project-URL: Bug Tracker, https://github.com/tradinghours/tradinghours-python/issues
Project-URL: Homepage, https://github.com/tradinghours/tradinghours-python
Provides-Extra: dev
Provides-Extra: s3
Provides-Extra: server
